{
    "MSNvB_stand.stl": [
        [
            -100.0,
            26.853,
            -20.0
        ],
        [
            0.0,
            86.4986,
            -3.0
        ]
    ],
    "MSNvB_buttons.stl": [
        [
            0.2,
            -10.2966,
            0.0
        ],
        [
            6.6,
            10.2966,
            3.0
        ]
    ],
    "MSNvB_lEnc.stl": [
        [
            -100.0,
            0.0,
            -20.0
        ],
        [
            0.0,
            100.0,
            0.0
        ]
    ],
    "MSNvB_top.stl": [
        [
            -102.0,
            -2.0,
            -3.0
        ],
        [
            2.0,
            102.0,
            5.0
        ]
    ],
    "MSNvB_cov.stl": [
        [
            -104.0,
            -4.0,
            -22.0
        ],
        [
            4.0,
            104.0,
            7.0
        ]
    ]
}